{
  "type": "minecraft:block",
  "pools": [
    {
      "bonus_rolls": 0.0,
      "entries": [
        {
          "type": "minecraft:item",
          "name": "minecraft:quartz"
        }
      ],
      "functions": [
        {
          "enchantment": "minecraft:fortune",
          "formula": "minecraft:ore_drops",
          "function": "minecraft:apply_bonus"
        }
      ],
      "rolls": 1.0
    },
    {
      "bonus_rolls": 0.0,
      "entries": [
        {
          "type": "minecraft:item",
          "name": "potionsplus:sulfur_shard"
        }
      ],
      "functions": [
        {
          "add": false,
          "count": {
            "type": "minecraft:uniform",
            "max": 2.0,
            "min": 0.0
          },
          "function": "minecraft:set_count"
        },
        {
          "enchantment": "minecraft:fortune",
          "formula": "minecraft:ore_drops",
          "function": "minecraft:apply_bonus"
        }
      ],
      "rolls": 1.0
    }
  ],
  "random_sequence": "potionsplus:blocks/sulfuric_nether_quartz_ore"
}