{
  "criteria": {
    "has_potion": {
      "conditions": {
        "items": [
          {
            "items": "minecraft:potion"
          }
        ]
      },
      "trigger": "minecraft:inventory_changed"
    },
    "has_the_recipe": {
      "conditions": {
        "recipe": "potionsplus:all_potions_duration_increase"
      },
      "trigger": "minecraft:recipe_unlocked"
    }
  },
  "requirements": [
    [
      "has_potion",
      "has_the_recipe"
    ]
  ],
  "rewards": {
    "recipes": [
      "potionsplus:all_potions_duration_increase"
    ]
  },
  "sends_telemetry_event": true
}